pls/__init__.py
pls/functions.py
pls/static/.pls/cc_instrument.sh
pls/static/.pls/export_gdb_or_lldb.sh
pls/static/.pls/git_clone.sh
pls/static/.pls/pls_h_dir/pls.h
pls/static/.vscode/launch.json
pls/static/.vscode/settings.json
pls/static/.vscode/tasks.json
plstest-0.1.dist-info/LICENSE
plstest-0.1.dist-info/METADATA
plstest-0.1.dist-info/WHEEL
plstest-0.1.dist-info/entry_points.txt
plstest-0.1.dist-info/top_level.txt
plstest-0.1.dist-info/RECORD
