Metadata-Version: 2.1
Name: plstest
Version: 0.1
Summary: C/C++ Build Tool
Author: Dima Korolev
Author-email: dima+test@current.ai
License-File: LICENSE
